pandas_cub/__init__.py
tests/__init__.py
tests/test_dataframe.py
pandas_cub-0.0.7.dist-info/LICENSE
pandas_cub-0.0.7.dist-info/METADATA
pandas_cub-0.0.7.dist-info/WHEEL
pandas_cub-0.0.7.dist-info/top_level.txt
pandas_cub-0.0.7.dist-info/RECORD
